pylamarzocco/__init__.py
pylamarzocco/const.py
pylamarzocco/exceptions.py
pylamarzocco/py.typed
pylamarzocco/clients/__init__.py
pylamarzocco/clients/_bluetooth.py
pylamarzocco/clients/_cloud.py
pylamarzocco/devices/__init__.py
pylamarzocco/devices/_machine.py
pylamarzocco/devices/_thing.py
pylamarzocco/models/__init__.py
pylamarzocco/models/_authentication.py
pylamarzocco/models/_bluetooth.py
pylamarzocco/models/_config.py
pylamarzocco/models/_general.py
pylamarzocco/models/_schedule.py
pylamarzocco/models/_statistics.py
pylamarzocco/models/_update.py
pylamarzocco/util/__init__.py
pylamarzocco/util/_authentication.py
pylamarzocco/util/_generic.py
pylamarzocco/util/_websocket.py
pylamarzocco-2.2.4.dist-info/licenses/LICENSE
pylamarzocco-2.2.4.dist-info/METADATA
pylamarzocco-2.2.4.dist-info/WHEEL
pylamarzocco-2.2.4.dist-info/top_level.txt
pylamarzocco-2.2.4.dist-info/RECORD
