Metadata-Version: 2.4
Name: pylamarzocco
Version: 2.2.4
Summary: A Python implementation of the La Marzocco API
Author-email: Josef Zweck <24647999+zweckj@users.noreply.github.com>
Maintainer-email: Josef Zweck <24647999+zweckj@users.noreply.github.com>
License: MIT
Project-URL: Homepage, https://github.com/zweckj/pylamarzocco
Project-URL: Repository, https://github.com/zweckj/pylamarzocco
Project-URL: Documentation, https://github.com/zweckj/pylamarzocco
Keywords: La Marzocco,lamarzocco,api,async,client
Classifier: Development Status :: 5 - Production/Stable
Classifier: Framework :: AsyncIO
Classifier: Intended Audience :: Developers
Classifier: Natural Language :: English
Classifier: License :: OSI Approved :: MIT License
Classifier: Programming Language :: Python
Classifier: Programming Language :: Python :: 3.12
Requires-Python: >=3.12
License-File: LICENSE
Requires-Dist: bleak>=0.20.0
Requires-Dist: aiohttp>=3.8
Requires-Dist: mashumaro>=3.17
Requires-Dist: cryptography>=41.0
Requires-Dist: bleak-retry-connector>=4.0.0
Provides-Extra: dev
Requires-Dist: covdefaults==2.3.0; extra == "dev"
Requires-Dist: coverage==7.6.7; extra == "dev"
Requires-Dist: syrupy==4.7.2; extra == "dev"
Requires-Dist: pytest==8.3.3; extra == "dev"
Requires-Dist: pytest-asyncio==0.24.0; extra == "dev"
Requires-Dist: pytest-cov==6.0.0; extra == "dev"
Requires-Dist: aioresponses==0.7.7; extra == "dev"
Dynamic: license-file
